ccpi/__init__.py
ccpi/cuda_kernels/TV_PD_GPU_kernels.cuh
ccpi/cuda_kernels/TV_ROF_GPU_kernels.cuh
ccpi/cuda_kernels/__init__.py
ccpi/filters/TV.py
ccpi/filters/__init__.py
ccpi/filters/diffusion.py
ccpi/filters/regularisers.py
ccpi/filters/regularisersCuPy.py
ccpi/filters/utils.py
ccpi/supp/__init__.py
ccpi/supp/qualitymetrics.py
ccpi_regularisation_cupy-24.1.0.dist-info/LICENSE
ccpi_regularisation_cupy-24.1.0.dist-info/METADATA
ccpi_regularisation_cupy-24.1.0.dist-info/WHEEL
ccpi_regularisation_cupy-24.1.0.dist-info/top_level.txt
ccpi_regularisation_cupy-24.1.0.dist-info/RECORD
