Metadata-Version: 2.1
Name: ccpi_regularisation_cupy
Version: 24.1.0
Summary: GPU-CuPy accelerated regularisation routines of CCPi-regularisation toolkit
Author-email: Daniil Kazantsev <daniil.kazantsev@diamond.ac.uk>, Edoardo Pasca <edoardo.pasca@stfc.ac.uk>
License: BSD-3-Clause
Project-URL: Repository, https://github.com/TomographicImaging/CCPi-Regularisation-Toolkit
Classifier: Development Status :: 4 - Beta
Classifier: License :: OSI Approved :: BSD License
Classifier: Programming Language :: Python :: 3.10
Classifier: Environment :: GPU :: NVIDIA CUDA
Requires-Python: >=3.10
License-File: LICENSE
Requires-Dist: cupy
Requires-Dist: numpy
Requires-Dist: pillow
Requires-Dist: pytest
Provides-Extra: dev
Requires-Dist: pytest; extra == "dev"
Requires-Dist: pytest-cov; extra == "dev"
Requires-Dist: pytest-xdist; extra == "dev"
Requires-Dist: pytest-benchmark; extra == "dev"
Requires-Dist: flake8; extra == "dev"
Requires-Dist: pyproject-flake8; extra == "dev"
Requires-Dist: pydocstyle; extra == "dev"
